movielst/API.py
movielst/API_util.py
movielst/__init__.py
movielst/config.py
movielst/database.py
movielst/movielst.py
movielst/omdb.py
movielst/tmdb.py
web/dependency.py
web/forms.py
web/main.py
web/static/default-poster.png
web/static/style.css
web/static/fonts/LICENSE.txt
web/static/fonts/README.txt
web/static/fonts/config.json
web/static/fonts/css/animation.css
web/static/fonts/css/fontello-codes.css
web/static/fonts/css/fontello-embedded.css
web/static/fonts/css/fontello-ie7-codes.css
web/static/fonts/css/fontello-ie7.css
web/static/fonts/css/fontello.css
web/static/fonts/font/fontello.eot
web/static/fonts/font/fontello.svg
web/static/fonts/font/fontello.ttf
web/static/fonts/font/fontello.woff
web/static/fonts/font/fontello.woff2
web/templates/home.html
web/templates/layout.html
web/templates/login.html
web/templates/movie.html
web/templates/play.html
web/templates/includes/_navbar.html
web/templates/includes/_navbar_settings.html
web/templates/settings/settings.html
web/templates/settings/users.html
movielst-2.5.0.dist-info/LICENSE
movielst-2.5.0.dist-info/METADATA
movielst-2.5.0.dist-info/WHEEL
movielst-2.5.0.dist-info/entry_points.txt
movielst-2.5.0.dist-info/top_level.txt
movielst-2.5.0.dist-info/RECORD
